Metadata-Version: 2.1
Name: ernest-nkunzimana-distributions
Version: 0.1
Summary: Gaussian distributions
License-File: license.txt
